<annotation>
	<folder>annotations_isabella</folder>
	<filename>frame_558000.jpg</filename>
	<path>F:\isa\labelimg\annotations_isabella\frame_558000.jpg</path>
	<source>
		<database>Unknown</database>
	</source>
	<size>
		<width>1920</width>
		<height>1080</height>
		<depth>3</depth>
	</size>
	<segmented>0</segmented>
	<object>
		<name>helmet</name>
		<pose>Unspecified</pose>
		<truncated>0</truncated>
		<difficult>0</difficult>
		<bndbox>
			<xmin>364</xmin>
			<ymin>361</ymin>
			<xmax>627</xmax>
			<ymax>592</ymax>
		</bndbox>
	</object>
	<object>
		<name>meat</name>
		<pose>Unspecified</pose>
		<truncated>0</truncated>
		<difficult>0</difficult>
		<bndbox>
			<xmin>822</xmin>
			<ymin>472</ymin>
			<xmax>1135</xmax>
			<ymax>816</ymax>
		</bndbox>
	</object>
	<object>
		<name>meat</name>
		<pose>Unspecified</pose>
		<truncated>0</truncated>
		<difficult>0</difficult>
		<bndbox>
			<xmin>964</xmin>
			<ymin>344</ymin>
			<xmax>1242</xmax>
			<ymax>607</ymax>
		</bndbox>
	</object>
	<object>
		<name>meat</name>
		<pose>Unspecified</pose>
		<truncated>0</truncated>
		<difficult>0</difficult>
		<bndbox>
			<xmin>977</xmin>
			<ymin>181</ymin>
			<xmax>1244</xmax>
			<ymax>394</ymax>
		</bndbox>
	</object>
	<object>
		<name>meat</name>
		<pose>Unspecified</pose>
		<truncated>0</truncated>
		<difficult>0</difficult>
		<bndbox>
			<xmin>1043</xmin>
			<ymin>19</ymin>
			<xmax>1245</xmax>
			<ymax>175</ymax>
		</bndbox>
	</object>
</annotation>
