<annotation>
	<folder>video1_frames</folder>
	<filename>frame_9000.3.jpg</filename>
	<path>/home/flow/Documents/graymatics/annotations_v2_agrosuper/video1_frames/frame_9000.3.jpg</path>
	<source>
		<database>Unknown</database>
	</source>
	<size>
		<width>1920</width>
		<height>1080</height>
		<depth>3</depth>
	</size>
	<segmented>0</segmented>
	<object>
		<name>meat</name>
		<pose>Unspecified</pose>
		<truncated>0</truncated>
		<difficult>0</difficult>
		<bndbox>
			<xmin>792</xmin>
			<ymin>12</ymin>
			<xmax>1030</xmax>
			<ymax>216</ymax>
		</bndbox>
	</object>
	<object>
		<name>meat</name>
		<pose>Unspecified</pose>
		<truncated>0</truncated>
		<difficult>0</difficult>
		<bndbox>
			<xmin>428</xmin>
			<ymin>168</ymin>
			<xmax>661</xmax>
			<ymax>601</ymax>
		</bndbox>
	</object>
	<object>
		<name>meat</name>
		<pose>Unspecified</pose>
		<truncated>1</truncated>
		<difficult>0</difficult>
		<bndbox>
			<xmin>707</xmin>
			<ymin>364</ymin>
			<xmax>1002</xmax>
			<ymax>1080</ymax>
		</bndbox>
	</object>
	<object>
		<name>meat</name>
		<pose>Unspecified</pose>
		<truncated>0</truncated>
		<difficult>0</difficult>
		<bndbox>
			<xmin>1463</xmin>
			<ymin>852</ymin>
			<xmax>1763</xmax>
			<ymax>1060</ymax>
		</bndbox>
	</object>
	<object>
		<name>meat</name>
		<pose>Unspecified</pose>
		<truncated>1</truncated>
		<difficult>0</difficult>
		<bndbox>
			<xmin>336</xmin>
			<ymin>735</ymin>
			<xmax>630</xmax>
			<ymax>1080</ymax>
		</bndbox>
	</object>
	<object>
		<name>helmet</name>
		<pose>Unspecified</pose>
		<truncated>1</truncated>
		<difficult>0</difficult>
		<bndbox>
			<xmin>1713</xmin>
			<ymin>81</ymin>
			<xmax>1920</xmax>
			<ymax>310</ymax>
		</bndbox>
	</object>
</annotation>
